seispack/Freq.py
seispack/PSD.py
seispack/__init__.py
seispack/_version.py
seispack/basic.py
seispack/common.py
seispack/data/__init__.py
seispack/data/kepler.py
seispack/hough/__init__.py
seispack/hough/asymptotic.py
seispack/hough/base.py
seispack/hough/core.py
seispack/hough/tables.py
seispack/hough/util.py
seispack/hough/tables/lambda_m-1.txt
seispack/hough/tables/lambda_m-2.txt
seispack/hough/tables/lambda_m-3.txt
seispack/hough/tables/lambda_m0.txt
seispack/hough/tables/lambda_m1.txt
seispack/hough/tables/lambda_m2.txt
seispack/hough/tables/lambda_m3.txt
seispack/slrg/Model.py
seispack/slrg/__init__.py
seispack/slrg/bg_tools.py
seispack/slrg/eacf.py
seispack/slrg/generate_spectra.py
seispack/slrg/plot_echelle.py
seispack/slrg/plot_echelle_image.py
seispack/slrg/plot_stretch.py
seispack/slrg/psd.py
seispack/slrg/scaling_law.py
seispack/slrg/stretch.py
seispack/tar/__init__.py
seispack/tar/generate_aTAR.py
seispack/tar/plot_stretch_rot.py
seispack-0.3.2.dist-info/licenses/LICENSE
seispack-0.3.2.dist-info/METADATA
seispack-0.3.2.dist-info/WHEEL
seispack-0.3.2.dist-info/top_level.txt
seispack-0.3.2.dist-info/RECORD
