Metadata-Version: 2.4
Name: seispack
Version: 0.3.2
Summary: Python Tools for asteroseismic data analysis
Author-email: Jérôme Ballot <jerome.ballot@irap.omp.eu>
License-Expression: CECILL-2.1
Project-URL: Homepage, https://gitlab.in2p3.fr/astero/seispack/
Project-URL: Issues, https://gitlab.in2p3.fr/astero/seispack/issues
Keywords: stellar physics,asteroseismology,data analysis
Classifier: Programming Language :: Python :: 3
Classifier: Operating System :: OS Independent
Requires-Python: >=3.10
License-File: LICENSE
Requires-Dist: numpy>=1.23
Requires-Dist: scipy>=1.15
Requires-Dist: matplotlib>=3.5
Requires-Dist: astropy
Requires-Dist: astroquery>=0.4.9
Requires-Dist: tqdm
Requires-Dist: importlib_resources
Dynamic: license-file
